pranavi_convert/__init__.py
pranavi_convert/converter.py
pranavi_convert-0.1.0.dist-info/licenses/LICENSE
pranavi_convert-0.1.0.dist-info/METADATA
pranavi_convert-0.1.0.dist-info/WHEEL
pranavi_convert-0.1.0.dist-info/top_level.txt
pranavi_convert-0.1.0.dist-info/RECORD
