Metadata-Version: 2.4
Name: pranavi-convert
Version: 0.1.0
Summary: A universal data converter (binary, hex, octal, ascii)
Home-page: https://github.com/yourgithubusername/pranavi-convert
Author: Puneeth Kumar
Author-email: your_email@example.com
Classifier: Programming Language :: Python :: 3
Classifier: License :: OSI Approved :: MIT License
Classifier: Operating System :: OS Independent
Requires-Python: >=3.6
License-File: LICENSE
Dynamic: author
Dynamic: author-email
Dynamic: classifier
Dynamic: description
Dynamic: description-content-type
Dynamic: home-page
Dynamic: license-file
Dynamic: requires-python
Dynamic: summary
